JaxLinOp/__init__.py
JaxLinOp-0.0.0.dist-info/LICENSE
JaxLinOp-0.0.0.dist-info/METADATA
JaxLinOp-0.0.0.dist-info/WHEEL
JaxLinOp-0.0.0.dist-info/top_level.txt
JaxLinOp-0.0.0.dist-info/RECORD
